{
  "ok": true,
  "data": [
    {
      "cursor": "1774537394000000158",
      "orderList": [
        {
          "assetChange": [
            {
              "coinAmount": "0.010000",
              "coinSymbol": "USDC",
              "direction": "OUT"
            }
          ],
          "chainSymbol": "OKB",
          "coinAmount": "0.010000",
          "coinSymbol": "USDC",
          "confirmedCount": "0",
          "direction": "OUT",
          "from": "0x1ef1034e7cd690b40a329bd64209ce563f95bb5c",
          "hideTxType": "0",
          "repeatTxType": "0",
          "serviceCharge": "2253037600135",
          "to": "0x74b7f16337b8972027f6196a17a631ac6de26d22",
          "txCreateTime": "1774577362000",
          "txHash": "0x99c122e592eaa50133f67b4360cd52f4a69c88670d195ed3f6d8c9fb7e721e81",
          "txStatus": "SUCCESS",
          "txTime": "1774577362000"
        },
        {
          "assetChange": [
            {
              "coinAmount": "0.010000",
              "coinSymbol": "USDC",
              "direction": "OUT"
            }
          ],
          "chainSymbol": "OKB",
          "coinAmount": "0.010000",
          "coinSymbol": "USDC",
          "confirmedCount": "0",
          "direction": "OUT",
          "from": "0x1ef1034e7cd690b40a329bd64209ce563f95bb5c",
          "hideTxType": "0",
          "repeatTxType": "0",
          "serviceCharge": "3591867469527",
          "to": "0x74b7f16337b8972027f6196a17a631ac6de26d22",
          "txCreateTime": "1774577319000",
          "txHash": "0xe32531d6baa6976e8badc0598348ba99a728af6deb8fd896584f3b0bda491104",
          "txStatus": "SUCCESS",
          "txTime": "1774577319000"
        },
        {
          "assetChange": [
            {
              "coinAmount": "0.020000",
              "coinSymbol": "USDC",
              "direction": "OUT"
            }
          ],
          "chainSymbol": "OKB",
          "coinAmount": "0.020000",
          "coinSymbol": "USDC",
          "confirmedCount": "0",
          "direction": "OUT",
          "from": "0x1ef1034e7cd690b40a329bd64209ce563f95bb5c",
          "hideTxType": "0",
          "repeatTxType": "0",
          "serviceCharge": "2872938373070",
          "to": "0x5c67869272f3d167c761dbbf0dc3901a1ff214d3",
          "txCreateTime": "1774539011000",
          "txHash": "0x05d6fdc18a3a583d555278236d1110816757e4434972410bc5ebec5d33d2f1aa",
          "txStatus": "SUCCESS",
          "txTime": "1774539011000"
        },
        {
          "assetChange": [
            {
              "coinAmount": "0.000007498383327232",
              "coinSymbol": "OKB",
              "direction": "IN"
            }
          ],
          "chainSymbol": "OKB",
          "coinAmount": "0.000007498383327232",
          "coinSymbol": "OKB",
          "confirmedCount": "0",
          "direction": "IN",
          "from": "0x5c67869272f3d167c761dbbf0dc3901a1ff214d3",
          "hideTxType": "0",
          "repeatTxType": "0",
          "serviceCharge": "32003600000000",
          "to": "0x1ef1034e7cd690b40a329bd64209ce563f95bb5c",
          "txCreateTime": "1774539004000",
          "txHash": "0xb3b0a3f8bc908625b5bfffa2026cb82307f77f2f1fd1426439b8f1712924cb93",
          "txStatus": "SUCCESS",
          "txTime": "1774539004000"
        },
        {
          "assetChange": [
            {
              "coinAmount": "0.020000",
              "coinSymbol": "USDC",
              "direction": "OUT"
            }
          ],
          "chainSymbol": "OKB",
          "coinAmount": "0.020000",
          "coinSymbol": "USDC",
          "confirmedCount": "0",
          "direction": "OUT",
          "from": "0x1ef1034e7cd690b40a329bd64209ce563f95bb5c",
          "hideTxType": "0",
          "repeatTxType": "0",
          "serviceCharge": "4106316253270",
          "to": "0x5c67869272f3d167c761dbbf0dc3901a1ff214d3",
          "txCreateTime": "1774538827000",
          "txHash": "0x316d2bcf2064f55f0d7ce1285b8fd270595aa5a95ad698ed8c131d4a504c3b00",
          "txStatus": "SUCCESS",
          "txTime": "1774538827000"
        },
        {
          "assetChange": [
            {
              "coinAmount": "0.000007498383327232",
              "coinSymbol": "OKB",
              "direction": "IN"
            }
          ],
          "chainSymbol": "OKB",
          "coinAmount": "0.000007498383327232",
          "coinSymbol": "OKB",
          "confirmedCount": "0",
          "direction": "IN",
          "from": "0x5c67869272f3d167c761dbbf0dc3901a1ff214d3",
          "hideTxType": "0",
          "repeatTxType": "0",
          "serviceCharge": "32003600000000",
          "to": "0x1ef1034e7cd690b40a329bd64209ce563f95bb5c",
          "txCreateTime": "1774538819000",
          "txHash": "0x62a25a538cd7145b72613a9e2ae7f86a85cfe9f8dc86e0b77aab3f3650709884",
          "txStatus": "SUCCESS",
          "txTime": "1774538819000"
        },
        {
          "assetChange": [
            {
              "coinAmount": "0.000007498383327232",
              "coinSymbol": "OKB",
              "direction": "IN"
            }
          ],
          "chainSymbol": "OKB",
          "coinAmount": "0.000007498383327232",
          "coinSymbol": "OKB",
          "confirmedCount": "0",
          "direction": "IN",
          "from": "0x5c67869272f3d167c761dbbf0dc3901a1ff214d3",
          "hideTxType": "0",
          "repeatTxType": "0",
          "serviceCharge": "32003600000000",
          "to": "0x1ef1034e7cd690b40a329bd64209ce563f95bb5c",
          "txCreateTime": "1774538661000",
          "txHash": "0x9b633b851b3c62061d9a53072175f2b5fec1fff6ac94996be0f9968e64b7c186",
          "txStatus": "SUCCESS",
          "txTime": "1774538661000"
        },
        {
          "assetChange": [
            {
              "coinAmount": "0.020000",
              "coinSymbol": "USDC",
              "direction": "OUT"
            }
          ],
          "chainSymbol": "OKB",
          "coinAmount": "0.020000",
          "coinSymbol": "USDC",
          "confirmedCount": "0",
          "direction": "OUT",
          "from": "0x1ef1034e7cd690b40a329bd64209ce563f95bb5c",
          "hideTxType": "0",
          "repeatTxType": "0",
          "serviceCharge": "6068448722251",
          "to": "0x5c67869272f3d167c761dbbf0dc3901a1ff214d3",
          "txCreateTime": "1774538165000",
          "txHash": "0x37e153c0445ee682f54fe5459cbd313e08e3fbaee82abb4db1ecfd87d82b2972",
          "txStatus": "SUCCESS",
          "txTime": "1774538165000"
        },
        {
          "assetChange": [
            {
              "coinAmount": "0.000007498383327232",
              "coinSymbol": "OKB",
              "direction": "IN"
            }
          ],
          "chainSymbol": "OKB",
          "coinAmount": "0.000007498383327232",
          "coinSymbol": "OKB",
          "confirmedCount": "0",
          "direction": "IN",
          "from": "0x5c67869272f3d167c761dbbf0dc3901a1ff214d3",
          "hideTxType": "0",
          "repeatTxType": "0",
          "serviceCharge": "32003600000000",
          "to": "0x1ef1034e7cd690b40a329bd64209ce563f95bb5c",
          "txCreateTime": "1774538158000",
          "txHash": "0xe651a33985dcef309e16847461e4c5ae7190e550d6592937e98ad56eeb46ba48",
          "txStatus": "SUCCESS",
          "txTime": "1774538158000"
        },
        {
          "assetChange": [
            {
              "coinAmount": "0.020000",
              "coinSymbol": "USDC",
              "direction": "OUT"
            }
          ],
          "chainSymbol": "OKB",
          "coinAmount": "0.020000",
          "coinSymbol": "USDC",
          "confirmedCount": "0",
          "direction": "OUT",
          "from": "0x1ef1034e7cd690b40a329bd64209ce563f95bb5c",
          "hideTxType": "0",
          "repeatTxType": "0",
          "serviceCharge": "2703645000000",
          "to": "0x5c67869272f3d167c761dbbf0dc3901a1ff214d3",
          "txCreateTime": "1774537404000",
          "txHash": "0x24dcb063344a1f9f5ae3691e5a991c8e2323bec772b0b52c021f6caed91c1aa5",
          "txStatus": "SUCCESS",
          "txTime": "1774537404000"
        }
      ]
    }
  ]
}
